Workbook

Sheet Declaration - Annex B
A1: 2002 Financial Forecasts Update
H2: Please return to SFEFC no later than 18 March 2002
A3: College Name: | C3: Text
A5: Address: | C5: Text
C6: Text
C7: Text
C8: Text
C9: Text
A11: Contact: | C11: Text
A13: Telephone: | C13: Text
A15: e-mail: | C15: Text
A17: Financial Forecast Return - Declaration
A19: The attached five worksheets represent an update on the financial forecasts for the college, based on the actual financial results to 31 January 2002 and other relevant information. I consider the revised forecasts to be a reasonable assessment of the College's projected financial position at the end of this financial year in light of the information available to me.
A26: Signed | B26: Text | D26: Principal and Accountable Officer | H26: Text | J26: Date

Sheet Commentary - Annex C
A1: 2002 Financial Forecasts Update
C3: Financial Commentary
A4: ='Table 1.0 I & E - Annex D'!A4 -> COLLEGE NAME
A6: Please provide a financial commentary for the Financial Forecast Update (FFU) in the box (or if necessary in an accompanying word document)
A8: Note: The commentary should be provided for all material changes from the original FFR for 2001/02.
A10: THIS MUST BE
A11: COMPLETED

Sheet Table 1.0 I & E - Annex D
A1: 2002 Financial Forecasts Update
A3: Table | B3: 1 | C3: Income and Expenditure Account (Consolidated)
A4: COLLEGE NAME | H4: Original FFR Forecast | I4: Mid-Year Update - Revised Outturn | J4: Variance | K4: Variance as % of original forecast | L4: Reason for variance where material (Normally > £50k and >10%)
C5: Contact: | D5: College Contact | H5: 2001-02 | I5: 2001-02
C6: Telephone: | D6: Contact Telephone | H6: £000 | I6: £000 | J6: £000 | K6: %
C8: Income
B9: 1 | C9: Funding Council Grants (excluding Bursaries and Access) | H9: 0 | I9: 0 | J9: =I9-H9 -> 0 | K9: =IF(H9=0,"N/A",(J9/H9)*100) -> N/A
B10: 2 | C10: Education Contracts (non-SFEFC funded) | H10: 0 | I10: 0 | J10: =I10-H10 -> 0 | K10: =IF(H10=0,"N/A",(J10/H10)*100) -> N/A
B11: 3 | C11: Tuition Fees (SFEFC Fundable Activity) | H11: 0 | I11: 0 | J11: =I11-H11 -> 0 | K11: =IF(H11=0,"N/A",(J11/H11)*100) -> N/A
B12: 4 | C12: Other Grant Income | H12: 0 | I12: 0 | J12: =I12-H12 -> 0 | K12: =IF(H12=0,"N/A",(J12/H12)*100) -> N/A
B13: 5 | C13: Other Operating Income | H13: 0 | I13: 0 | J13: =I13-H13 -> 0 | K13: =IF(H13=0,"N/A",(J13/H13)*100) -> N/A
B14: 6 | C14: Endowment and Investment Income, Interest Receivable | H14: 0 | I14: 0 | J14: =I14-H14 -> 0 | K14: =IF(H14=0,"N/A",(J14/H14)*100) -> N/A
B15: 7 | C15: Total Income | H15: =SUM(H9:H14) -> 0 | I15: =SUM(I9:I14) -> 0 | J15: =I15-H15 -> 0 | K15: =IF(H15=0,"N/A",(J15/H15)*100) -> N/A
C17: Expenditure
B18: =B15+1 -> 8 | C18: Normal Staff Costs | H18: 0 | I18: 0 | J18: =I18-H18 -> 0 | K18: =IF(H18=0,"N/A",(J18/H18)*100) -> N/A
B19: =B18+1 -> 9 | C19: Exceptional restructuring costs | H19: 0 | I19: 0 | J19: =I19-H19 -> 0 | K19: =IF(H19=0,"N/A",(J19/H19)*100) -> N/A
B20: 10 | C20: Other Operating Expenses | H20: 0 | I20: 0 | J20: =I20-H20 -> 0 | K20: =IF(H20=0,"N/A",(J20/H20)*100) -> N/A
B21: =B20+1 -> 11 | C21: Depreciation | H21: 0 | I21: 0 | J21: =I21-H21 -> 0 | K21: =IF(H21=0,"N/A",(J21/H21)*100) -> N/A
B22: =B21+1 -> 12 | C22: Interest Payable | H22: 0 | I22: 0 | J22: =I22-H22 -> 0 | K22: =IF(H22=0,"N/A",(J22/H22)*100) -> N/A
B23: =B22+1 -> 13 | C23: Total Expenditure (excluding Bursaries and Access Payments) | H23: =SUM(H18:H22) -> 0 | I23: =SUM(I18:I22) -> 0 | J23: =I23-H23 -> 0 | K23: =IF(H23=0,"N/A",(J23/H23)*100) -> N/A
B25: =B23+1 -> 14 | C25: Surplus/(Deficit) after Depreciation of Assets at | H25: =H15-H23 -> 0 | I25: =I15-I23 -> 0 | J25: =I25-H25 -> 0 | K25: =IF(H25=0,"N/A",(J25/H25)*100) -> N/A
C26: Valuation and Before Disposal of Assets and Tax
B28: =B25+1 -> 15 | C28: Gain on sale of assets | H28: 0 | I28: 0 | J28: =I28-H28 -> 0 | K28: =IF(H28=0,"N/A",(J28/H28)*100) -> N/A
B29: =B28+1 -> 16 | C29: Loss on sale of assets | H29: 0 | I29: 0 | J29: =I29-H29 -> 0 | K29: =IF(H29=0,"N/A",(J29/H29)*100) -> N/A
B31: =B29+840 -> 856 | C31: Surplus/(Deficit) after Depreciation of Assets at | H31: =H25+H28-H29 -> 0 | I31: =I25+I28-I29 -> 0 | J31: =I31-H31 -> 0 | K31: =IF(H31=0,"N/A",(J31/H31)*100) -> N/A
C32: Valuation and Disposal of Assets and Before Tax
B34: =B31+1 -> 857 | C34: Taxation | H34: 0 | I34: 0 | J34: =I34-H34 -> 0 | K34: =IF(H34=0,"N/A",(J34/H34)*100) -> N/A
B36: =B34+1 -> 858 | C36: Minority Interest | H36: 0 | I36: 0 | J36: =I36-H36 -> 0 | K36: =IF(H36=0,"N/A",(J36/H36)*100) -> N/A
B38: =B36+1 -> 859 | C38: Surplus/(Deficit) after Depreciation of Assets at | H38: =H31-H34-H36 -> 0 | I38: =I31-I34-I36 -> 0 | J38: =I38-H38 -> 0 | K38: =IF(H38=0,"N/A",(J38/H38)*100) -> N/A
C39: Valuation, Disposal of Assets and Tax
C41: Note of Historical Cost Surpluses and Deficits
B43: =B38+1 -> 860 | C43: Surplus/(Deficit) after Depreciation of Assets at | H43: =H38 -> 0 | I43: =I38 -> 0 | J43: =I43-H43 -> 0 | K43: =IF(H43=0,"N/A",(J43/H43)*100) -> N/A
C44: Valuation and Tax
B46: =B43+1 -> 861 | C46: Transfer (to)/from revaluation reserve | H46: 0 | I46: 0 | J46: =I46-H46 -> 0 | K46: =IF(H46=0,"N/A",(J46/H46)*100) -> N/A
B48: =B46+1 -> 862 | C48: Historical Cost Surplus/(Deficit) after Tax | H48: =SUM(H43:H47) -> 0 | I48: =SUM(I43:I47) -> 0 | J48: =I48-H48 -> 0 | K48: =IF(H48=0,"N/A",(J48/H48)*100) -> N/A
B50: =B48+1 -> 863 | C50: Transfer (to)/from restricted funds | H50: 0 | I50: 0 | J50: =I50-H50 -> 0 | K50: =IF(H50=0,"N/A",(J50/H50)*100) -> N/A
B51: =B50+1 -> 864 | C51: Transfer (to)/from designated reserves | H51: 0 | I51: 0 | J51: =I51-H51 -> 0 | K51: =IF(H51=0,"N/A",(J51/H51)*100) -> N/A
B52: =B51+1 -> 865 | C52: Amount carried forward to I&E account | H52: =SUM(H48:H51) -> 0 | I52: =SUM(I48:I51) -> 0 | J52: =I52-H52 -> 0 | K52: =IF(H52=0,"N/A",(J52/H52)*100) -> N/A
C54: Bursary and Access Funds
B56: =B52+1 -> 866 | C56: Bursary Funding | H56: 0 | I56: 0 | J56: =I56-H56 -> 0 | K56: =IF(H56=0,"N/A",(J56/H56)*100) -> N/A
B57: =B56+1 -> 867 | C57: Payments from Bursary Funds | H57: 0 | I57: 0 | J57: =I57-H57 -> 0 | K57: =IF(H57=0,"N/A",(J57/H57)*100) -> N/A
B58: =B57+1 -> 868 | C58: (Over)/Under-use of Bursary Funds in year | H58: =H56-H57 -> 0 | I58: =I56-I57 -> 0 | J58: =I58-H58 -> 0 | K58: =IF(H58=0,"N/A",(J58/H58)*100) -> N/A
B59: =B58+1 -> 869 | C59: Access Funding | H59: 0 | I59: 0 | J59: =I59-H59 -> 0 | K59: =IF(H59=0,"N/A",(J59/H59)*100) -> N/A
B60: =B59+1 -> 870 | C60: Payments from Access Funds | H60: 0 | I60: 0 | J60: =I60-H60 -> 0 | K60: =IF(H60=0,"N/A",(J60/H60)*100) -> N/A
B61: =B60+1 -> 871 | C61: (Over)/Under-use of Access Funds in year | H61: =H59-H60 -> 0 | I61: =I59-I60 -> 0 | J61: =I61-H61 -> 0 | K61: =IF(H61=0,"N/A",(J61/H61)*100) -> N/A

Sheet Table 2.0 BS - Annex E
A1: ='Table 1.0 I & E - Annex D'!A1 -> 2002 Financial Forecasts Update
A3: Table | B3: 2 | C3: Consolidated Balance Sheet
A4: ='Table 1.0 I & E - Annex D'!A4 -> COLLEGE NAME | H4: Original FFR Forecast | I4: Mid-Year Update - Revised Outturn | J4: Variance | K4: Variance as % of original forecast | L4: Reason for variance where material (Normally > £50k and >10%)
H5: 2001-02 | I5: 2001-02
C6: Fixed Assets | H6: £000 | I6: £000 | J6: £000
B7: 1 | C7: Inherited land and buildings | H7: 0 | I7: 0 | J7: =I7-H7 -> 0 | K7: =IF(H7=0,"N/A",(J7/H7)*100) -> N/A
B8: 2 | C8: Land and buildings financed by Capital Grant | H8: 0 | I8: 0 | J8: =I8-H8 -> 0 | K8: =IF(H8=0,"N/A",(J8/H8)*100) -> N/A
B9: 3 | C9: Land and Buildings financed by PFI | H9: 0 | I9: 0 | J9: =I9-H9 -> 0 | K9: =IF(H9=0,"N/A",(J9/H9)*100) -> N/A
B10: 4 | C10: Other Land and Buildings acquired post-incorporation | H10: 0 | I10: 0 | J10: =I10-H10 -> 0 | K10: =IF(H10=0,"N/A",(J10/H10)*100) -> N/A
B11: 5 | C11: Equipment | H11: 0 | I11: 0 | J11: =I11-H11 -> 0 | K11: =IF(H11=0,"N/A",(J11/H11)*100) -> N/A
B12: 6 | C12: Investments | H12: 0 | I12: 0 | J12: =I12-H12 -> 0 | K12: =IF(H12=0,"N/A",(J12/H12)*100) -> N/A
B13: 7 | C13: Total Fixed Assets | H13: =SUM(H7:H12) -> 0 | I13: =SUM(I7:I12) -> 0 | J13: =I13-H13 -> 0 | K13: =IF(H13=0,"N/A",(J13/H13)*100) -> N/A
B15: 8 | C15: Endowment Asset Investments | H15: 0 | I15: 0 | J15: =I15-H15 -> 0 | K15: =IF(H15=0,"N/A",(J15/H15)*100) -> N/A
C17: Current Assets
B18: 9 | C18: Stocks and Stores in Hand | H18: 0 | I18: 0 | J18: =I18-H18 -> 0 | K18: =IF(H18=0,"N/A",(J18/H18)*100) -> N/A
B19: 10 | C19: Debtors | H19: 0 | I19: 0 | J19: =I19-H19 -> 0 | K19: =IF(H19=0,"N/A",(J19/H19)*100) -> N/A
B20: 11 | C20: Investments | H20: 0 | I20: 0 | J20: =I20-H20 -> 0 | K20: =IF(H20=0,"N/A",(J20/H20)*100) -> N/A
B21: 12 | C21: Cash at Bank/in Hand | H21: 0 | I21: 0 | J21: =I21-H21 -> 0 | K21: =IF(H21=0,"N/A",(J21/H21)*100) -> N/A
B22: 13 | C22: Unspent/(overspent) balance on bursaries and access | H22: 0 | I22: 0 | J22: =I22-H22 -> 0 | K22: =IF(H22=0,"N/A",(J22/H22)*100) -> N/A
B23: 14 | C23: Total Current Assets | H23: =SUM(H18:H22) -> 0 | I23: =SUM(I18:I22) -> 0 | J23: =I23-H23 -> 0 | K23: =IF(H23=0,"N/A",(J23/H23)*100) -> N/A
C25: Creditors: Amounts Falling Due Within One Year
B26: 15 | C26: Creditors | H26: 0 | I26: 0 | J26: =I26-H26 -> 0 | K26: =IF(H26=0,"N/A",(J26/H26)*100) -> N/A
B27: 16 | C27: LA Loans | H27: 0 | I27: 0 | J27: =I27-H27 -> 0 | K27: =IF(H27=0,"N/A",(J27/H27)*100) -> N/A
B28: 17 | C28: Bank Overdrafts (shown as positive) | H28: 0 | I28: 0 | J28: =I28-H28 -> 0 | K28: =IF(H28=0,"N/A",(J28/H28)*100) -> N/A
B29: 18 | C29: Other Bank Loans | H29: 0 | I29: 0 | J29: =I29-H29 -> 0 | K29: =IF(H29=0,"N/A",(J29/H29)*100) -> N/A
B30: 19 | C30: Finance Lease Obligations | H30: 0 | I30: 0 | J30: =I30-H30 -> 0 | K30: =IF(H30=0,"N/A",(J30/H30)*100) -> N/A
B31: 20 | C31: Obligations under PFI | H31: 0 | I31: 0 | J31: =I31-H31 -> 0 | K31: =IF(H31=0,"N/A",(J31/H31)*100) -> N/A
B32: 21 | C32: Unspent/(overspent) balance on bursaries and access | H32: 0 | I32: 0 | J32: =I32-H32 -> 0 | K32: =IF(H32=0,"N/A",(J32/H32)*100) -> N/A
B33: 22 | C33: Total Amounts Falling Due Within One Year | H33: =SUM(H26:H32) -> 0 | I33: =SUM(I26:I32) -> 0 | J33: =I33-H33 -> 0 | K33: =IF(H33=0,"N/A",(J33/H33)*100) -> N/A
B35: 23 | C35: Net Current Assets/(Liabilities) | H35: =H23-H33 -> 0 | I35: =I23-I33 -> 0 | J35: =I35-H35 -> 0 | K35: =IF(H35=0,"N/A",(J35/H35)*100) -> N/A
B37: 24 | C37: Total Assets Less Current Liabilities | H37: =H13+H15+H35 -> 0 | I37: =I13+I15+I35 -> 0 | J37: =I37-H37 -> 0 | K37: =IF(H37=0,"N/A",(J37/H37)*100) -> N/A
C39: Creditors: Amounts Falling Due After More Than One Year
B40: 25 | C40: LA Loans | H40: 0 | I40: 0 | J40: =I40-H40 -> 0 | K40: =IF(H40=0,"N/A",(J40/H40)*100) -> N/A
B41: 26 | C41: Bank Loans | H41: 0 | I41: 0 | J41: =I41-H41 -> 0 | K41: =IF(H41=0,"N/A",(J41/H41)*100) -> N/A
B42: 27 | C42: Finance Lease Obligations | H42: 0 | I42: 0 | J42: =I42-H42 -> 0 | K42: =IF(H42=0,"N/A",(J42/H42)*100) -> N/A
B43: 28 | C43: Obligations under PFI | H43: 0 | I43: 0 | J43: =I43-H43 -> 0 | K43: =IF(H43=0,"N/A",(J43/H43)*100) -> N/A
B44: 29 | C44: Total Amounts Falling Due After More Than One Year | H44: =SUM(H40:H43) -> 0 | I44: =SUM(I40:I43) -> 0 | J44: =I44-H44 -> 0 | K44: =IF(H44=0,"N/A",(J44/H44)*100) -> N/A
C46: Provisions for Liabilities and Charges
B47: 30 | C47: Total Provision for Liabilities and Charges | H47: 0 | I47: 0 | J47: =I47-H47 -> 0 | K47: =IF(H47=0,"N/A",(J47/H47)*100) -> N/A
B49: 31 | C49: Total Net Assets | H49: =H37-H44-H47 -> 0 | I49: =I37-I44-I47 -> 0 | J49: =I49-H49 -> 0 | K49: =IF(H49=0,"N/A",(J49/H49)*100) -> N/A
C51: Deferred Capital Grants
B52: 32 | C52: SOEID/SFEFC | H52: 0 | I52: 0 | J52: =I52-H52 -> 0 | K52: =IF(H52=0,"N/A",(J52/H52)*100) -> N/A
B53: 33 | C53: ERDF | H53: 0 | I53: 0 | J53: =I53-H53 -> 0 | K53: =IF(H53=0,"N/A",(J53/H53)*100) -> N/A
B54: 34 | C54: Millennium | H54: 0 | I54: 0 | J54: =I54-H54 -> 0 | K54: =IF(H54=0,"N/A",(J54/H54)*100) -> N/A
B55: 35 | C55: Other (including disposal of assets treated as def grant) | H55: 0 | I55: 0 | J55: =I55-H55 -> 0 | K55: =IF(H55=0,"N/A",(J55/H55)*100) -> N/A
B56: 36 | C56: Total Deferred Grants | H56: =SUM(H52:H55) -> 0 | I56: =SUM(I52:I55) -> 0 | J56: =I56-H56 -> 0 | K56: =IF(H56=0,"N/A",(J56/H56)*100) -> N/A
C58: Endowments
B59: 37 | C59: Endowments | H59: =H15 -> 0 | I59: =I15 -> 0 | J59: =I59-H59 -> 0 | K59: =IF(H59=0,"N/A",(J59/H59)*100) -> N/A
C61: Reserves
B62: 38 | C62: Revaluation Reserve | H62: 0 | I62: 0 | J62: =I62-H62 -> 0 | K62: =IF(H62=0,"N/A",(J62/H62)*100) -> N/A
B63: 39 | C63: Restricted Reserve | H63: 0 | I63: 0 | J63: =I63-H63 -> 0 | K63: =IF(H63=0,"N/A",(J63/H63)*100) -> N/A
B64: 40 | C64: Designated Reserve | H64: 0 | I64: 0 | J64: =I64-H64 -> 0 | K64: =IF(H64=0,"N/A",(J64/H64)*100) -> N/A
B65: 41 | C65: Income and Expenditure Account | H65: 0 | I65: 0 | J65: =I65-H65 -> 0 | K65: =IF(H65=0,"N/A",(J65/H65)*100) -> N/A
B66: 42 | C66: Minority Interest | H66: 0 | I66: 0 | J66: =I66-H66 -> 0 | K66: =IF(H66=0,"N/A",(J66/H66)*100) -> N/A
B67: 43 | C67: Total Reserves | H67: =SUM(H62:H66) -> 0 | I67: =SUM(I62:I66) -> 0 | J67: =I67-H67 -> 0 | K67: =IF(H67=0,"N/A",(J67/H67)*100) -> N/A
B69: 44 | C69: Total Funds | H69: =H56+H59+H67 -> 0 | I69: =I56+I59+I67 -> 0 | J69: =I69-H69 -> 0 | K69: =K49 -> N/A
B71: 45 | C71: College Income & Expenditure Account (only input | H71: =H65 -> 0 | I71: =I65 -> 0 | J71: =J65 -> 0 | K71: =IF(H71=0,"N/A",(J71/H71)*100) -> N/A
C72: where this differs from Group)
C74: >>>>>>>>> THESE CELLS MUST BE ZERO >>>>>>>> | H74: =H49-H69 -> 0 | I74: =I49-I69 -> 0 | J74: =J49-J69 -> 0 | K74: =IF(H74=0,"N/A",(J74/H74)*100) -> N/A

Sheet Table 3.0 CF - Annex F
A1: ='Table 1.0 I & E - Annex D'!A1 -> 2002 Financial Forecasts Update
A3: Table | B3: 3 | C3: Operating Cash Flow (Consolidated) | H3: Refer to FFR submitted in (or around) August 2001
A4: ='Table 1.0 I & E - Annex D'!A4 -> COLLEGE NAME | H4: August | I4: September | J4: October | K4: November | L4: December | M4: January | N4: February | O4: March | P4: April | Q4: May | R4: June | S4: July | T4: Total
C5: ORIGINAL CASH FORECAST 2001-02 | G5: £'000
C6: Income
B7: 1 | C7: SFEFC funding (including bursaries and access) | H7: 0 | I7: 0 | J7: 0 | K7: 0 | L7: 0 | M7: 0 | N7: 0 | O7: 0 | P7: 0 | Q7: 0 | R7: 0 | S7: 0 | T7: =SUM(H7:S7) -> 0
B8: 2 | C8: Other grants received | H8: 0 | I8: 0 | J8: 0 | K8: 0 | L8: 0 | M8: 0 | N8: 0 | O8: 0 | P8: 0 | Q8: 0 | R8: 0 | S8: 0 | T8: =SUM(H8:S8) -> 0
B9: 3 | C9: Other cash received | H9: 0 | I9: 0 | J9: 0 | K9: 0 | L9: 0 | M9: 0 | N9: 0 | O9: 0 | P9: 0 | Q9: 0 | R9: 0 | S9: 0 | T9: =SUM(H9:S9) -> 0
B10: 4 | C10: Total cash in | H10: =SUM(H7:H9) -> 0 | I10: =SUM(I7:I9) -> 0 | J10: =SUM(J7:J9) -> 0 | K10: =SUM(K7:K9) -> 0 | L10: =SUM(L7:L9) -> 0 | M10: =SUM(M7:M9) -> 0 | N10: =SUM(N7:N9) -> 0 | O10: =SUM(O7:O9) -> 0 | ... T10: =SUM(T7:T9) -> 0
C11: Expenditure
B12: 5 | C12: Payroll | H12: 0 | I12: 0 | J12: 0 | K12: 0 | L12: 0 | M12: 0 | N12: 0 | O12: 0 | P12: 0 | Q12: 0 | R12: 0 | S12: 0 | T12: =SUM(H12:S12) -> 0
B13: 6 | C13: Other payments (including bursaries & access, excluding interest) | H13: 0 | I13: 0 | J13: 0 | K13: 0 | L13: 0 | M13: 0 | N13: 0 | O13: 0 | P13: 0 | Q13: 0 | R13: 0 | S13: 0 | T13: =SUM(H13:S13) -> 0
B14: 7 | C14: Interest payments | H14: 0 | I14: 0 | J14: 0 | K14: 0 | L14: 0 | M14: 0 | N14: 0 | O14: 0 | P14: 0 | Q14: 0 | R14: 0 | S14: 0 | T14: =SUM(H14:S14) -> 0
B15: 8 | C15: Total cash out | H15: =SUM(H12:H14) -> 0 | I15: =SUM(I12:I14) -> 0 | J15: =SUM(J12:J14) -> 0 | K15: =SUM(K12:K14) -> 0 | L15: =SUM(L12:L14) -> 0 | M15: =SUM(M12:M14) -> 0 | N15: =SUM(N12:N14) -> 0 | O15: =SUM(O12:O14) -> 0 | ... T15: =SUM(T12:T14) -> 0
B16: 9 | C16: Cash taken off/(put on) deposit | H16: 0 | I16: 0 | J16: 0 | K16: 0 | L16: 0 | M16: 0 | N16: 0 | O16: 0 | P16: 0 | Q16: 0 | R16: 0 | S16: 0 | T16: =SUM(H16:S16) -> 0
B17: 10 | C17: Net cash inflow/(outflow) | H17: =H10-H15+H16 -> 0 | I17: =I10-I15+I16 -> 0 | J17: =J10-J15+J16 -> 0 | K17: =K10-K15+K16 -> 0 | L17: =L10-L15+L16 -> 0 | M17: =M10-M15+M16 -> 0 | N17: =N10-N15+N16 -> 0 | O17: =O10-O15+O16 -> 0 | ... S17: =S10-S15+S16 -> 0 | T17: =SUM(H17:S17) -> 0
B18: 11 | C18: Balance b/f (cash and overdraft) | H18: 0 | I18: =H19 -> 0 | J18: =I19 -> 0 | K18: =J19 -> 0 | L18: =K19 -> 0 | M18: =L19 -> 0 | N18: =M19 -> 0 | O18: =N19 -> 0 | P18: =O19 -> 0 | ... S18: =R19 -> 0 | T18: =H18 -> 0
B19: 12 | C19: Balance c/f (cash and overdraft) | H19: =SUM(H17:H18) -> 0 | I19: =SUM(I17:I18) -> 0 | J19: =SUM(J17:J18) -> 0 | K19: =SUM(K17:K18) -> 0 | L19: =SUM(L17:L18) -> 0 | M19: =SUM(M17:M18) -> 0 | N19: =SUM(N17:N18) -> 0 | O19: =SUM(O17:O18) -> 0 | ... S19: =SUM(S17:S18) -> 0 | T19: =S19 -> 0
C21: Financed by:
B22: 13 | C22: Cash | H22: 0 | I22: 0 | J22: 0 | K22: 0 | L22: 0 | M22: 0 | N22: 0 | O22: 0 | P22: 0 | Q22: 0 | R22: 0 | S22: 0 | T22: =S22 -> 0
B23: 14 | C23: (Overdraft/Short-term bank loan)-show as negative | H23: 0 | I23: 0 | J23: 0 | K23: 0 | L23: 0 | M23: 0 | N23: 0 | O23: 0 | P23: 0 | Q23: 0 | R23: 0 | S23: 0 | T23: =S23 -> 0
B24: 15 | C24: Total financing | H24: =SUM(H22:H23) -> 0 | I24: =SUM(I22:I23) -> 0 | J24: =SUM(J22:J23) -> 0 | K24: =SUM(K22:K23) -> 0 | L24: =SUM(L22:L23) -> 0 | M24: =SUM(M22:M23) -> 0 | N24: =SUM(N22:N23) -> 0 | O24: =SUM(O22:O23) -> 0 | ... T24: =SUM(T22:T23) -> 0
C25: These cells should be zero | H25: =H24-H19 -> 0 | I25: =I24-I19 -> 0 | J25: =J24-J19 -> 0 | K25: =K24-K19 -> 0 | L25: =L24-L19 -> 0 | M25: =M24-M19 -> 0 | N25: =N24-N19 -> 0 | O25: =O24-O19 -> 0 | ... T25: =T24-T19 -> 0
C26: This cell should be zero (reconciliation with balance sheet) | T26: =T19-('Table 2.0 BS - Annex E'!H20+'Table 2.0 BS - Annex E'!H21+'Table 2.0 BS - Annex E'!H22) -> 0
C28: ACTUAL/REVISED FORECAST 2001-2002 | H28: August | I28: September | J28: October | K28: November | L28: December | M28: January | N28: February | O28: March | P28: April | Q28: May | R28: June | S28: July | T28: Total
C29: Income | H29: Actual | I29: Actual | J29: Actual | K29: Actual | L29: Actual | M29: Actual | N29: Forecast | O29: Forecast | P29: Forecast | Q29: Forecast | R29: Forecast | S29: Forecast
B30: 16 | C30: SFEFC funding (including bursaries and access) | H30: 0 | I30: 0 | J30: 0 | K30: 0 | L30: 0 | M30: 0 | N30: 0 | O30: 0 | P30: 0 | Q30: 0 | R30: 0 | S30: 0 | T30: =SUM(H30:S30) -> 0
B31: 17 | C31: Other grants received | H31: 0 | I31: 0 | J31: 0 | K31: 0 | L31: 0 | M31: 0 | N31: 0 | O31: 0 | P31: 0 | Q31: 0 | R31: 0 | S31: 0 | T31: =SUM(H31:S31) -> 0
B32: 18 | C32: Other cash received | H32: 0 | I32: 0 | J32: 0 | K32: 0 | L32: 0 | M32: 0 | N32: 0 | O32: 0 | P32: 0 | Q32: 0 | R32: 0 | S32: 0 | T32: =SUM(H32:S32) -> 0
B33: 19 | C33: Total cash in | H33: =SUM(H30:H32) -> 0 | I33: =SUM(I30:I32) -> 0 | J33: =SUM(J30:J32) -> 0 | K33: =SUM(K30:K32) -> 0 | L33: =SUM(L30:L32) -> 0 | M33: =SUM(M30:M32) -> 0 | N33: =SUM(N30:N32) -> 0 | O33: =SUM(O30:O32) -> 0 | ... T33: =SUM(T30:T32) -> 0
C34: Expenditure
B35: 20 | C35: Payroll | H35: 0 | I35: 0 | J35: 0 | K35: 0 | L35: 0 | M35: 0 | N35: 0 | O35: 0 | P35: 0 | Q35: 0 | R35: 0 | S35: 0 | T35: =SUM(H35:S35) -> 0
B36: 21 | C36: Other payments (including bursaries & access, excluding interest) | H36: 0 | I36: 0 | J36: 0 | K36: 0 | L36: 0 | M36: 0 | N36: 0 | O36: 0 | P36: 0 | Q36: 0 | R36: 0 | S36: 0 | T36: =SUM(H36:S36) -> 0
B37: 22 | C37: Interest payments | H37: 0 | I37: 0 | J37: 0 | K37: 0 | L37: 0 | M37: 0 | N37: 0 | O37: 0 | P37: 0 | Q37: 0 | R37: 0 | S37: 0 | T37: =SUM(H37:S37) -> 0
B38: 23 | C38: Total cash out | H38: =SUM(H35:H37) -> 0 | I38: =SUM(I35:I37) -> 0 | J38: =SUM(J35:J37) -> 0 | K38: =SUM(K35:K37) -> 0 | L38: =SUM(L35:L37) -> 0 | M38: =SUM(M35:M37) -> 0 | N38: =SUM(N35:N37) -> 0 | O38: =SUM(O35:O37) -> 0 | ... T38: =SUM(T35:T37) -> 0
B39: 24 | C39: Cash taken off/(put on) deposit | H39: 0 | I39: 0 | J39: 0 | K39: 0 | L39: 0 | M39: 0 | N39: 0 | O39: 0 | P39: 0 | Q39: 0 | R39: 0 | S39: 0 | T39: =SUM(H39:S39) -> 0
B40: 25 | C40: Net cash inflow/(outflow) | H40: =H33-H38+H39 -> 0 | I40: =I33-I38+I39 -> 0 | J40: =J33-J38+J39 -> 0 | K40: =K33-K38+K39 -> 0 | L40: =L33-L38+L39 -> 0 | M40: =M33-M38+M39 -> 0 | N40: =N33-N38+N39 -> 0 | O40: =O33-O38+O39 -> 0 | ... S40: =S33-S38+S39 -> 0 | T40: =SUM(H40:S40) -> 0
B41: 26 | C41: Balance b/f (cash and overdraft) | H41: 0 | I41: =H42 -> 0 | J41: =I42 -> 0 | K41: =J42 -> 0 | L41: =K42 -> 0 | M41: =L42 -> 0 | N41: =M42 -> 0 | O41: =N42 -> 0 | P41: =O42 -> 0 | ... S41: =R42 -> 0 | T41: =H41 -> 0
B42: 27 | C42: Balance c/f (cash and overdraft) | H42: =SUM(H40:H41) -> 0 | I42: =SUM(I40:I41) -> 0 | J42: =SUM(J40:J41) -> 0 | K42: =SUM(K40:K41) -> 0 | L42: =SUM(L40:L41) -> 0 | M42: =SUM(M40:M41) -> 0 | N42: =SUM(N40:N41) -> 0 | O42: =SUM(O40:O41) -> 0 | ... S42: =SUM(S40:S41) -> 0 | T42: =S42 -> 0
C44: Financed by:
B45: 28 | C45: Cash | H45: 0 | I45: 0 | J45: 0 | K45: 0 | L45: 0 | M45: 0 | N45: 0 | O45: 0 | P45: 0 | Q45: 0 | R45: 0 | S45: 0 | T45: =S45 -> 0
B46: 29 | C46: (Overdraft/Short-term bank loan)-show as negative | H46: 0 | I46: 0 | J46: 0 | K46: 0 | L46: 0 | M46: 0 | N46: 0 | O46: 0 | P46: 0 | Q46: 0 | R46: 0 | S46: 0 | T46: =S46 -> 0
B47: 30 | C47: Total financing | H47: =SUM(H45:H46) -> 0 | I47: =SUM(I45:I46) -> 0 | J47: =SUM(J45:J46) -> 0 | K47: =SUM(K45:K46) -> 0 | L47: =SUM(L45:L46) -> 0 | M47: =SUM(M45:M46) -> 0 | N47: =SUM(N45:N46) -> 0 | O47: =SUM(O45:O46) -> 0 | ... T47: =SUM(T45:T46) -> 0
C48: These cells should be zero | H48: =H47-H42 -> 0 | I48: =I47-I42 -> 0 | J48: =J47-J42 -> 0 | K48: =K47-K42 -> 0 | L48: =L47-L42 -> 0 | M48: =M47-M42 -> 0 | N48: =N47-N42 -> 0 | O48: =O47-O42 -> 0 | ... T48: =T47-T42 -> 0
C49: This cell should be zero (reconciliation with balance sheet) | T49: =T42-('Table 2.0 BS - Annex E'!I20+'Table 2.0 BS - Annex E'!I21+'Table 2.0 BS - Annex E'!I22) -> 0
B51: 31 | C51: Difference between actual/revised forecast of closing balance | H51: =H42-H19 -> 0 | I51: =I42-I19 -> 0 | J51: =J42-J19 -> 0 | K51: =K42-K19 -> 0 | L51: =L42-L19 -> 0 | M51: =M42-M19 -> 0 | N51: =N42-N19 -> 0 | O51: =O42-O19 -> 0 | ... T51: =T42-T19 -> 0
C52: and original forecast
C53: Percentage variance | H53: =IF(H19=0,"N/A",(H51/H19)*100) -> N/A | I53: =IF(I19=0,"N/A",(I51/I19)*100) -> N/A | J53: =IF(J19=0,"N/A",(J51/J19)*100) -> N/A | K53: =IF(K19=0,"N/A",(K51/K19)*100) -> N/A | L53: =IF(L19=0,"N/A",(L51/L19)*100) -> N/A | M53: =IF(M19=0,"N/A",(M51/M19)*100) -> N/A | N53: =IF(N19=0,"N/A",(N51/N19)*100) -> N/A | O53: =IF(O19=0,"N/A",(O51/O19)*100) -> N/A | ... T53: =IF(T19=0,"N/A",(T51/T19)*100) -> N/A
H55: Reasons for variances where material (normally > £50k and >10%). Ignore timing differences which reverse in subsequent months.
