Workbook

Sheet Table G.1
A1: Table G.1: Budget Overview
A2: You should complete only the Contractual Budget & Leonardo da Vinci Grant figures relating to your project, Expenditure Realised will be automatically completed from Table G.2
B4: Contractual Budget (Euro) | C4: Leonardo da Vinci Grant (Euro) | D4: Expenditure Realised (Euro)
A5: A. Staff Costs
A6: B. Operating Costs
A7: 1. Travel | D7: ='Table G.2'!$B9 -> 0
A8: 2. ICT | D8: ='Table G.2'!$B13 -> 0
A9: 3. Production | D9: ='Table G.2'!$B14 -> 4
A10: 4. Overheads
A11: 5. Other | D11: ='Table G.2'!$B16 -> 0
A12: Sub-Total B | B12: =SUM(B7:B11) -> 0 | C12: =SUM(C7:C11) -> 0 | D12: =SUM(D7:D11) -> 4
A13: C. Subcontracting Costs
A14: Subcontracting 1 | D14: ='Table G.2'!$B19 -> 0
A15: Subcontracting 2 | D15: ='Table G.2'!$B20 -> 0
A16: Subcontracting 3 | D16: ='Table G.2'!$B21 -> 0
A17: Subcontracting 4 | D17: ='Table G.2'!$B22 -> 0
A18: Subcontracting 5 | D18: ='Table G.2'!$B23 -> 0
A19: Subcontracting 6 | D19: ='Table G.2'!$B24 -> 0
A20: Sub-Total C | B20: =SUM(B14:B19) -> 0 | C20: =SUM(C14:C19) -> 0 | D20: =SUM(D14:D19) -> 0
A21: TOTAL | B21: =SUM(B5,B12,B20) -> 0 | C21: =SUM(C5,C12,C20) -> 0 | D21: =SUM(D12,D20) -> 4

Sheet Table G.2
A1: Table G.2: Breakdown of Expenses already incurred by partner (Euro)
A2: This table is automatically completed using the contents of Tables G.4-G.8
A4: Partner Number  | B4: Total | C4: 1 | D4: 2 | E4: 3 | F4: 4 | G4: 5 | H4: 6 | I4: 7 | J4: 8 | K4: 9 | L4: 10 | M4: 11 | N4: 12 | O4: 13 | P4: 14 | Q4: 15 | R4: 16 | S4: 17 | T4: 18 | U4: 19 | V4: 20
A5: A. Staff Costs
A6: B. Operating Costs
A7: 1a. Travel | B7: =SUM(C7:V7) -> 0 | C7: =SUMIF('Table G.4'!$C$5:$C$142,C4,'Table G.4'!$N$5:$N$142) -> 0 | D7: =SUMIF('Table G.4'!$C$5:$C$142,D4,'Table G.4'!$N$5:$N$142) -> 0 | E7: =SUMIF('Table G.4'!$C$5:$C$142,E4,'Table G.4'!$N$5:$N$142) -> 0 | F7: =SUMIF('Table G.4'!$C$5:$C$142,F4,'Table G.4'!$N$5:$N$142) -> 0 | G7: =SUMIF('Table G.4'!$C$5:$C$142,G4,'Table G.4'!$N$5:$N$142) -> 0 | H7: =SUMIF('Table G.4'!$C$5:$C$142,H4,'Table G.4'!$N$5:$N$142) -> 0 | I7: =SUMIF('Table G.4'!$C$5:$C$142,I4,'Table G.4'!$N$5:$N$142) -> 0 | J7: =SUMIF('Table G.4'!$C$5:$C$142,J4,'Table G.4'!$N$5:$N$142) -> 0 | ... V7: =SUMIF('Table G.4'!$C$5:$C$142,V4,'Table G.4'!$N$5:$N$142) -> 0
A8: 1b. Subsistence | B8: =SUM(C8:V8) -> 0 | C8: =SUMIF('Table G.4'!$C$5:$C$142,C4,'Table G.4'!$O$5:$O$142) -> 0 | D8: =SUMIF('Table G.4'!$C$5:$C$142,D4,'Table G.4'!$O$5:$O$142) -> 0 | E8: =SUMIF('Table G.4'!$C$5:$C$142,E4,'Table G.4'!$O$5:$O$142) -> 0 | F8: =SUMIF('Table G.4'!$C$5:$C$142,F4,'Table G.4'!$O$5:$O$142) -> 0 | G8: =SUMIF('Table G.4'!$C$5:$C$142,G4,'Table G.4'!$O$5:$O$142) -> 0 | H8: =SUMIF('Table G.4'!$C$5:$C$142,H4,'Table G.4'!$O$5:$O$142) -> 0 | I8: =SUMIF('Table G.4'!$C$5:$C$142,I4,'Table G.4'!$O$5:$O$142) -> 0 | J8: =SUMIF('Table G.4'!$C$5:$C$142,J4,'Table G.4'!$O$5:$O$142) -> 0 | ... V8: =SUMIF('Table G.4'!$C$5:$C$142,V4,'Table G.4'!$O$5:$O$142) -> 0
A9: 1. Travel & Subsistence | B9: =SUM(C9:V9) -> 0 | C9: =SUM(C7:C8) -> 0 | D9: =SUM(D7:D8) -> 0 | E9: =SUM(E7:E8) -> 0 | F9: =SUM(F7:F8) -> 0 | G9: =SUM(G7:G8) -> 0 | H9: =SUM(H7:H8) -> 0 | I9: =SUM(I7:I8) -> 0 | J9: =SUM(J7:J8) -> 0 | ... V9: =SUM(V7:V8) -> 0
A10: 5a. Software, etc | B10: =SUM(C10:V10) -> 0 | C10: =SUMIF('Table G.5.a'!$C$6:$C$40,C4,'Table G.5.a'!$H$6:$H$40) -> 0 | D10: =SUMIF('Table G.5.a'!$C$6:$C$40,D4,'Table G.5.a'!$H$6:$H$40) -> 0 | E10: =SUMIF('Table G.5.a'!$C$6:$C$40,E4,'Table G.5.a'!$H$6:$H$40) -> 0 | F10: =SUMIF('Table G.5.a'!$C$6:$C$40,F4,'Table G.5.a'!$H$6:$H$40) -> 0 | G10: =SUMIF('Table G.5.a'!$C$6:$C$40,G4,'Table G.5.a'!$H$6:$H$40) -> 0 | H10: =SUMIF('Table G.5.a'!$C$6:$C$40,H4,'Table G.5.a'!$H$6:$H$40) -> 0 | I10: =SUMIF('Table G.5.a'!$C$6:$C$40,I4,'Table G.5.a'!$H$6:$H$40) -> 0 | J10: =SUMIF('Table G.5.a'!$C$6:$C$40,J4,'Table G.5.a'!$H$6:$H$40) -> 0 | ... V10: =SUMIF('Table G.5.a'!$C$6:$C$40,V4,'Table G.5.a'!$H$6:$H$40) -> 0
A11: 5b. Purchase (Hardware) | B11: =SUM(C11:V11) -> 0 | C11: =SUMIF('Table G.5.b'!$C$6:$C$40,C4,'Table G.5.b'!$K$6:$K$40) -> 0 | D11: =SUMIF('Table G.5.b'!$C$6:$C$40,D4,'Table G.5.b'!$K$6:$K$40) -> 0 | E11: =SUMIF('Table G.5.b'!$C$6:$C$40,E4,'Table G.5.b'!$K$6:$K$40) -> 0 | F11: =SUMIF('Table G.5.b'!$C$6:$C$40,F4,'Table G.5.b'!$K$6:$K$40) -> 0 | G11: =SUMIF('Table G.5.b'!$C$6:$C$40,G4,'Table G.5.b'!$K$6:$K$40) -> 0 | H11: =SUMIF('Table G.5.b'!$C$6:$C$40,H4,'Table G.5.b'!$K$6:$K$40) -> 0 | I11: =SUMIF('Table G.5.b'!$C$6:$C$40,I4,'Table G.5.b'!$K$6:$K$40) -> 0 | J11: =SUMIF('Table G.5.b'!$C$6:$C$40,J4,'Table G.5.b'!$K$6:$K$40) -> 0 | ... V11: =SUMIF('Table G.5.b'!$C$6:$C$40,V4,'Table G.5.b'!$K$6:$K$40) -> 0
A12: 5c. Hire/Lease (Hardware) | B12: =SUM(C12:V12) -> 0 | C12: =SUMIF('Table G.5.c'!$C$6:$C$40,C4,'Table G.5.c'!$I$6:$I$40) -> 0 | D12: =SUMIF('Table G.5.c'!$C$6:$C$40,D4,'Table G.5.c'!$I$6:$I$40) -> 0 | E12: =SUMIF('Table G.5.c'!$C$6:$C$40,E4,'Table G.5.c'!$I$6:$I$40) -> 0 | F12: =SUMIF('Table G.5.c'!$C$6:$C$40,F4,'Table G.5.c'!$I$6:$I$40) -> 0 | G12: =SUMIF('Table G.5.c'!$C$6:$C$40,G4,'Table G.5.c'!$I$6:$I$40) -> 0 | H12: =SUMIF('Table G.5.c'!$C$6:$C$40,H4,'Table G.5.c'!$I$6:$I$40) -> 0 | I12: =SUMIF('Table G.5.c'!$C$6:$C$40,I4,'Table G.5.c'!$I$6:$I$40) -> 0 | J12: =SUMIF('Table G.5.c'!$C$6:$C$40,J4,'Table G.5.c'!$I$6:$I$40) -> 0 | ... V12: =SUMIF('Table G.5.c'!$C$6:$C$40,V4,'Table G.5.c'!$I$6:$I$40) -> 0
A13: 2. ICT | B13: =SUM(C13:V13) -> 0 | C13: =SUM(C10:C12) -> 0 | D13: =SUM(D10:D12) -> 0 | E13: =SUM(E10:E12) -> 0 | F13: =SUM(F10:F12) -> 0 | G13: =SUM(G10:G12) -> 0 | H13: =SUM(H10:H12) -> 0 | I13: =SUM(I10:I12) -> 0 | J13: =SUM(J10:J12) -> 0 | ... V13: =SUM(V10:V12) -> 0
A14: 3. Production | B14: =SUM(C14:V14) -> 4 | C14: =SUMIF('Table G.6'!$C$5:$C$39,C4,'Table G.6'!$H$5:$H$39) -> 0 | D14: =SUMIF('Table G.6'!$C$5:$C$39,D4,'Table G.6'!$H$5:$H$39) -> 0 | E14: =SUMIF('Table G.6'!$C$5:$C$39,E4,'Table G.6'!$H$5:$H$39) -> 0 | F14: =4 -> 4 | G14: =SUMIF('Table G.6'!$C$5:$C$39,G4,'Table G.6'!$H$5:$H$39) -> 0 | H14: =SUMIF('Table G.6'!$C$5:$C$39,H4,'Table G.6'!$H$5:$H$39) -> 0 | I14: =SUMIF('Table G.6'!$C$5:$C$39,I4,'Table G.6'!$H$5:$H$39) -> 0 | J14: =SUMIF('Table G.6'!$C$5:$C$39,J4,'Table G.6'!$H$5:$H$39) -> 0 | K14: =SUMIF('Table G.6'!$C$5:$C$39,K4,'Table G.6'!$H$5:$H$39) -> 0 | L14: =SUMIF('Table G.6'!$C$5:$C$39,L4,'Table G.6'!$H$5:$H$39) -> 0 | M14: =SUMIF('Table G.6'!$C$5:$C$39,M4,'Table G.6'!$H$5:$H$39) -> 0 | N14: =SUMIF('Table G.6'!$C$5:$C$39,N4,'Table G.6'!$H$5:$H$39) -> 0 | ... V14: =SUMIF('Table G.6'!$C$5:$C$39,V4,'Table G.6'!$H$5:$H$39) -> 0
A15: 4. Overheads
A16: 5. Other | B16: =SUM(C16:V16) -> 0 | C16: =SUMIF('Table G.7'!$C$5:$C$39,C4,'Table G.7'!$H$5:$H$39) -> 0 | D16: =SUMIF('Table G.7'!$C$5:$C$39,D4,'Table G.7'!$H$5:$H$39) -> 0 | E16: =SUMIF('Table G.7'!$C$5:$C$39,E4,'Table G.7'!$H$5:$H$39) -> 0 | F16: =SUMIF('Table G.7'!$C$5:$C$39,F4,'Table G.7'!$H$5:$H$39) -> 0 | G16: =SUMIF('Table G.7'!$C$5:$C$39,G4,'Table G.7'!$H$5:$H$39) -> 0 | H16: =SUMIF('Table G.7'!$C$5:$C$39,H4,'Table G.7'!$H$5:$H$39) -> 0 | I16: =SUMIF('Table G.7'!$C$5:$C$39,I4,'Table G.7'!$H$5:$H$39) -> 0 | J16: =SUMIF('Table G.7'!$C$5:$C$39,J4,'Table G.7'!$H$5:$H$39) -> 0 | ... V16: =SUMIF('Table G.7'!$C$5:$C$39,V4,'Table G.7'!$H$5:$H$39) -> 0
A17: Sub-Total B | B17: =SUM(B9,B13,B14,B16) -> 4 | C17: =SUM(C9,C13,C14,C16) -> 0 | D17: =SUM(D9,D13,D14,D16) -> 0 | E17: =SUM(E9,E13,E14,E16) -> 0 | F17: =SUM(F9,F13,F14,F16) -> 4 | G17: =SUM(G9,G13,G14,G16) -> 0 | H17: =SUM(H9,H13,H14,H16) -> 0 | I17: =SUM(I9,I13,I14,I16) -> 0 | ... V17: =SUM(V9,V13,V14,V16) -> 0
A18: C. Subcontracting Costs
A19: Subcontracting 1 | B19: =SUM(C19:V19) -> 0 | C19: =SUMIF('Table G.8'!$C$5:$C$54,C$4,'Table G.8'!$I$5:$I$54) -> 0 | D19: =SUMIF('Table G.8'!$C$5:$C$54,D$4,'Table G.8'!$I$5:$I$54) -> 0 | E19: =SUMIF('Table G.8'!$C$5:$C$54,E$4,'Table G.8'!$I$5:$I$54) -> 0 | F19: =SUMIF('Table G.8'!$C$5:$C$54,F$4,'Table G.8'!$I$5:$I$54) -> 0 | G19: =SUMIF('Table G.8'!$C$5:$C$54,G$4,'Table G.8'!$I$5:$I$54) -> 0 | H19: =SUMIF('Table G.8'!$C$5:$C$54,H$4,'Table G.8'!$I$5:$I$54) -> 0 | I19: =SUMIF('Table G.8'!$C$5:$C$54,I$4,'Table G.8'!$I$5:$I$54) -> 0 | J19: =SUMIF('Table G.8'!$C$5:$C$54,J$4,'Table G.8'!$I$5:$I$54) -> 0 | ... V19: =SUMIF('Table G.8'!$C$5:$C$54,V$4,'Table G.8'!$I$5:$I$54) -> 0
A20: Subcontracting 2 | B20: =SUM(C20:V20) -> 0 | C20: =SUMIF('Table G.8'!$C$5:$C$54,C$4,'Table G.8'!$J$5:$J$54) -> 0 | D20: =SUMIF('Table G.8'!$C$5:$C$54,D$4,'Table G.8'!$J$5:$J$54) -> 0 | E20: =SUMIF('Table G.8'!$C$5:$C$54,E$4,'Table G.8'!$J$5:$J$54) -> 0 | F20: =SUMIF('Table G.8'!$C$5:$C$54,F$4,'Table G.8'!$J$5:$J$54) -> 0 | G20: =SUMIF('Table G.8'!$C$5:$C$54,G$4,'Table G.8'!$J$5:$J$54) -> 0 | H20: =SUMIF('Table G.8'!$C$5:$C$54,H$4,'Table G.8'!$J$5:$J$54) -> 0 | I20: =SUMIF('Table G.8'!$C$5:$C$54,I$4,'Table G.8'!$J$5:$J$54) -> 0 | J20: =SUMIF('Table G.8'!$C$5:$C$54,J$4,'Table G.8'!$J$5:$J$54) -> 0 | ... V20: =SUMIF('Table G.8'!$C$5:$C$54,V$4,'Table G.8'!$J$5:$J$54) -> 0
A21: Subcontracting 3 | B21: =SUM(C21:V21) -> 0 | C21: =SUMIF('Table G.8'!$C$5:$C$54,C$4,'Table G.8'!$K$5:$K$54) -> 0 | D21: =SUMIF('Table G.8'!$C$5:$C$54,D$4,'Table G.8'!$K$5:$K$54) -> 0 | E21: =SUMIF('Table G.8'!$C$5:$C$54,E$4,'Table G.8'!$K$5:$K$54) -> 0 | F21: =SUMIF('Table G.8'!$C$5:$C$54,F$4,'Table G.8'!$K$5:$K$54) -> 0 | G21: =SUMIF('Table G.8'!$C$5:$C$54,G$4,'Table G.8'!$K$5:$K$54) -> 0 | H21: =SUMIF('Table G.8'!$C$5:$C$54,H$4,'Table G.8'!$K$5:$K$54) -> 0 | I21: =SUMIF('Table G.8'!$C$5:$C$54,I$4,'Table G.8'!$K$5:$K$54) -> 0 | J21: =SUMIF('Table G.8'!$C$5:$C$54,J$4,'Table G.8'!$K$5:$K$54) -> 0 | ... V21: =SUMIF('Table G.8'!$C$5:$C$54,V$4,'Table G.8'!$K$5:$K$54) -> 0
A22: Subcontracting 4 | B22: =SUM(C22:V22) -> 0 | C22: =SUMIF('Table G.8'!$C$5:$C$54,C$4,'Table G.8'!$L$5:$L$54) -> 0 | D22: =SUMIF('Table G.8'!$C$5:$C$54,D$4,'Table G.8'!$L$5:$L$54) -> 0 | E22: =SUMIF('Table G.8'!$C$5:$C$54,E$4,'Table G.8'!$L$5:$L$54) -> 0 | F22: =SUMIF('Table G.8'!$C$5:$C$54,F$4,'Table G.8'!$L$5:$L$54) -> 0 | G22: =SUMIF('Table G.8'!$C$5:$C$54,G$4,'Table G.8'!$L$5:$L$54) -> 0 | H22: =SUMIF('Table G.8'!$C$5:$C$54,H$4,'Table G.8'!$L$5:$L$54) -> 0 | I22: =SUMIF('Table G.8'!$C$5:$C$54,I$4,'Table G.8'!$L$5:$L$54) -> 0 | J22: =SUMIF('Table G.8'!$C$5:$C$54,J$4,'Table G.8'!$L$5:$L$54) -> 0 | ... V22: =SUMIF('Table G.8'!$C$5:$C$54,V$4,'Table G.8'!$L$5:$L$54) -> 0
A23: Subcontracting 5 | B23: =SUM(C23:V23) -> 0 | C23: =SUMIF('Table G.8'!$C$5:$C$54,C$4,'Table G.8'!$M$5:$M$54) -> 0 | D23: =SUMIF('Table G.8'!$C$5:$C$54,D$4,'Table G.8'!$M$5:$M$54) -> 0 | E23: =SUMIF('Table G.8'!$C$5:$C$54,E$4,'Table G.8'!$M$5:$M$54) -> 0 | F23: =SUMIF('Table G.8'!$C$5:$C$54,F$4,'Table G.8'!$M$5:$M$54) -> 0 | G23: =SUMIF('Table G.8'!$C$5:$C$54,G$4,'Table G.8'!$M$5:$M$54) -> 0 | H23: =SUMIF('Table G.8'!$C$5:$C$54,H$4,'Table G.8'!$M$5:$M$54) -> 0 | I23: =SUMIF('Table G.8'!$C$5:$C$54,I$4,'Table G.8'!$M$5:$M$54) -> 0 | J23: =SUMIF('Table G.8'!$C$5:$C$54,J$4,'Table G.8'!$M$5:$M$54) -> 0 | ... V23: =SUMIF('Table G.8'!$C$5:$C$54,V$4,'Table G.8'!$M$5:$M$54) -> 0
A24: Subcontracting 6 | B24: =SUM(C24:V24) -> 0 | C24: =SUMIF('Table G.8'!$C$5:$C$54,C$4,'Table G.8'!$N$5:$N$54) -> 0 | D24: =SUMIF('Table G.8'!$C$5:$C$54,D$4,'Table G.8'!$N$5:$N$54) -> 0 | E24: =SUMIF('Table G.8'!$C$5:$C$54,E$4,'Table G.8'!$N$5:$N$54) -> 0 | F24: =SUMIF('Table G.8'!$C$5:$C$54,F$4,'Table G.8'!$N$5:$N$54) -> 0 | G24: =SUMIF('Table G.8'!$C$5:$C$54,G$4,'Table G.8'!$N$5:$N$54) -> 0 | H24: =SUMIF('Table G.8'!$C$5:$C$54,H$4,'Table G.8'!$N$5:$N$54) -> 0 | I24: =SUMIF('Table G.8'!$C$5:$C$54,I$4,'Table G.8'!$N$5:$N$54) -> 0 | J24: =SUMIF('Table G.8'!$C$5:$C$54,J$4,'Table G.8'!$N$5:$N$54) -> 0 | ... V24: =SUMIF('Table G.8'!$C$5:$C$54,V$4,'Table G.8'!$N$5:$N$54) -> 0
A25: Sub-Total C | B25: =SUM(B19:B24) -> 0 | C25: =SUM(C19:C24) -> 0 | D25: =SUM(D19:D24) -> 0 | E25: =SUM(E19:E24) -> 0 | F25: =SUM(F19:F24) -> 0 | G25: =SUM(G19:G24) -> 0 | H25: =SUM(H19:H24) -> 0 | I25: =SUM(I19:I24) -> 0 | ... V25: =SUM(V19:V24) -> 0
A26: TOTAL | B26: =SUM(B17,B25) -> 4 | C26: =SUM(C17,C25) -> 0 | D26: =SUM(D17,D25) -> 0 | E26: =SUM(E17,E25) -> 0 | F26: =SUM(F17,F25) -> 4 | G26: =SUM(G17,G25) -> 0 | H26: =SUM(H17,H25) -> 0 | I26: =SUM(I17,I25) -> 0 | ... V26: =SUM(V17,V25) -> 0
A32: `

Sheet Table G.3
A1: Table G.3: Details of Bank Transfers between the Contractor and its Partners
A3: Partner No. | B3: Partner Name | C3: Amount of the Payment (EUR) | D3: Date the contractor made the payment (dd/mm/yyyy) | E3: Currency Used

Sheet Table G.4
A1: Table G.4: Travel and Subsistence Expenses
A2: Total: | B2: =SUM(P5:P142) -> 0
A4: Item No. | B4: Partner | C4: Partner No. | D4: Name | E4: From (dd/mm/yyyy) | F4: To (dd/mm/yyyy) | G4: Duration (days) | H4: City | I4: Country Code | J4: City | K4: Country Code | L4: Objective of the trip | M4: Means of transport (+ type of fare) | N4: Travel Cost (Euro) | O4: Subsistence Costs (Euro) | P4: Total Travel & Subsistence (Euro)
P5: =N5+O5 -> 0
P6: =N6+O6 -> 0
P7: =N7+O7 -> 0
P8: =N8+O8 -> 0
P9: =N9+O9 -> 0
P10: =N10+O10 -> 0
P11: =N11+O11 -> 0
P12: =N12+O12 -> 0
P13: =N13+O13 -> 0
P14: =N14+O14 -> 0
P15: =N15+O15 -> 0
P16: =N16+O16 -> 0
... P142: =N142+O142 -> 0

Sheet Table G.5.a
A1: Table G.5.a: ICT Expenses
A2: Connection, Software and other computer & audio visual costs (except for Equipment)
A3: Total: | B3: =SUM(H6:H40) -> 0
A5: Item No. | B5: Partner | C5: Partner No. | D5: Type of cost (please give full details) | E5: Cost (Euro) | F5: Purpose | G5: Degree of use for the project (in %) | H5: Total Costs (Euro)
H6: =E6*G6 -> 0
H7: =E7*G7 -> 0
H8: =E8*G8 -> 0
H9: =E9*G9 -> 0
H10: =E10*G10 -> 0
H11: =E11*G11 -> 0
H12: =E12*G12 -> 0
H13: =E13*G13 -> 0
H14: =E14*G14 -> 0
H15: =E15*G15 -> 0
H16: =E16*G16 -> 0
H17: =E17*G17 -> 0
... H40: =E40*G40 -> 0

Sheet Table G.5.b
A1: Table G.5.b: ICT Expenses
A2: Computer and audio-visual equipment purchased within the framework of the project
A3: Total: | B3: =SUM(K6:K40) -> 0
A5: Item No. | B5: Partner | C5: Partner No. | D5: Nature and Specification | E5: Purpose | F5: Period of use for the project (in months) | G5: Purchase Cost (Euro) | H5: Purchase Date | I5: Depreciation Costs (Euro) | J5: Degree of use for the project (in %) | K5: Total Cost (Euro)
I6: =IF(G6>=10000,G6/60*F6,G6/36*F6) -> 0 | K6: =I6*J6 -> 0
I7: =IF(G7>=10000,G7/60*F7,G7/36*F7) -> 0 | K7: =I7*J7 -> 0
I8: =IF(G8>=10000,G8/60*F8,G8/36*F8) -> 0 | K8: =I8*J8 -> 0
I9: =IF(G9>=10000,G9/60*F9,G9/36*F9) -> 0 | K9: =I9*J9 -> 0
I10: =IF(G10>=10000,G10/60*F10,G10/36*F10) -> 0 | K10: =I10*J10 -> 0
I11: =IF(G11>=10000,G11/60*F11,G11/36*F11) -> 0 | K11: =I11*J11 -> 0
I12: =IF(G12>=10000,G12/60*F12,G12/36*F12) -> 0 | K12: =I12*J12 -> 0
I13: =IF(G13>=10000,G13/60*F13,G13/36*F13) -> 0 | K13: =I13*J13 -> 0
I14: =IF(G14>=10000,G14/60*F14,G14/36*F14) -> 0 | K14: =I14*J14 -> 0
I15: =IF(G15>=10000,G15/60*F15,G15/36*F15) -> 0 | K15: =I15*J15 -> 0
I16: =IF(G16>=10000,G16/60*F16,G16/36*F16) -> 0 | K16: =I16*J16 -> 0
I17: =IF(G17>=10000,G17/60*F17,G17/36*F17) -> 0 | K17: =I17*J17 -> 0
... I40: =IF(G40>=10000,G40/60*F40,G40/36*F40) -> 0 | K40: =I40*J40 -> 0

Sheet Table G.5.c
A1: Table G.5.c: ICT Expenses
A2: Computer and audio-visual equipment hired or leased within the framework of the project
A3: Total: | B3: =SUM(I6:I40) -> 0
A5: Item No. | B5: Partner | C5: Partner No. | D5: Nature and Specification | E5: Purpose | F5: Duration of hire or lease (in months) | G5: Monthly Hire/Lease Cost (Euro) | H5: Degree of use for the project (in %) | I5: Total Cost (Euro)
I6: =SUM(F6*G6)*H6 -> 0
I7: =SUM(F7*G7)*H7 -> 0
I8: =SUM(F8*G8)*H8 -> 0
I9: =SUM(F9*G9)*H9 -> 0
I10: =SUM(F10*G10)*H10 -> 0
I11: =SUM(F11*G11)*H11 -> 0
I12: =SUM(F12*G12)*H12 -> 0
I13: =SUM(F13*G13)*H13 -> 0
I14: =SUM(F14*G14)*H14 -> 0
I15: =SUM(F15*G15)*H15 -> 0
I16: =SUM(F16*G16)*H16 -> 0
I17: =SUM(F17*G17)*H17 -> 0
... I40: =SUM(F40*G40)*H40 -> 0

Sheet Table G.6
A1: Table G.6: Production Expenses
A2: Total: | B2: =SUM(H5:H39) -> 0
A4: Item No. | B4: Partner | C4: Partner No. | D4: Nature and Specification | E4: Purpose | F4: Unit Cost (Euro) | G4: Degree of use for the project (in %) | H4: Total Cost (Euro)
H5: =F5*G5 -> 0
H6: =F6*G6 -> 0
H7: =F7*G7 -> 0
H8: =F8*G8 -> 0
H9: =F9*G9 -> 0
H10: =F10*G10 -> 0
H11: =F11*G11 -> 0
H12: =F12*G12 -> 0
H13: =F13*G13 -> 0
H14: =F14*G14 -> 0
H15: =F15*G15 -> 0
H16: =F16*G16 -> 0
... H39: =F39*G39 -> 0

Sheet Table G.7
A1: Table G.7: Other Expenses / Costs
A2: Total: | B2: =SUM(H5:H39) -> 0
A4: Item No. | B4: Partner | C4: Partner No. | D4: Nature and Specification | E4: Purpose | F4: Unit Cost (Euro) | G4: Degree of use for the project (in %) | H4: Total Cost (Euro)
H5: =F5*G5 -> 0
H6: =F6*G6 -> 0
H7: =F7*G7 -> 0
H8: =F8*G8 -> 0
H9: =F9*G9 -> 0
H10: =F10*G10 -> 0
H11: =F11*G11 -> 0
H12: =F12*G12 -> 0
H13: =F13*G13 -> 0
H14: =F14*G14 -> 0
H15: =F15*G15 -> 0
H16: =F16*G16 -> 0
... H39: =F39*G39 -> 0

Sheet Table G.8
A1: Table G.8: Sub-contracting Expenses / Costs
A2: Total: | B2: =SUM(H5:H54) -> 0
F3: Subcontracting dates | I3: Subcontracting (self-calculating summaries-locked cells)
A4: Item No. | B4: Partner | C4: Partner No. | D4: Sub-contracted work | E4: Sub-contracting Package No. | F4: Start Date (dd/mm/yyyy) | G4: End Date (dd/mm/yyyy) | H4: Sub-contracting cost (Euro) | I4: 1 | J4: 2 | K4: 3 | L4: 4 | M4: 5 | N4: 6
I5: =SUMIF($E5,$I$4,$H5) -> 0 | J5: =SUMIF($E5,$J$4,$H5) -> 0 | K5: =SUMIF($E5,$K$4,$H5) -> 0 | L5: =SUMIF($E5,$L$4,$H5) -> 0 | M5: =SUMIF($E5,$M$4,$H5) -> 0 | N5: =SUMIF($E5,$N$4,$H5) -> 0
I6: =SUMIF($E6,$I$4,$H6) -> 0 | J6: =SUMIF($E6,$J$4,$H6) -> 0 | K6: =SUMIF($E6,$K$4,$H6) -> 0 | L6: =SUMIF($E6,$L$4,$H6) -> 0 | M6: =SUMIF($E6,$M$4,$H6) -> 0 | N6: =SUMIF($E6,$N$4,$H6) -> 0
I7: =SUMIF($E7,$I$4,$H7) -> 0 | J7: =SUMIF($E7,$J$4,$H7) -> 0 | K7: =SUMIF($E7,$K$4,$H7) -> 0 | L7: =SUMIF($E7,$L$4,$H7) -> 0 | M7: =SUMIF($E7,$M$4,$H7) -> 0 | N7: =SUMIF($E7,$N$4,$H7) -> 0
I8: =SUMIF($E8,$I$4,$H8) -> 0 | J8: =SUMIF($E8,$J$4,$H8) -> 0 | K8: =SUMIF($E8,$K$4,$H8) -> 0 | L8: =SUMIF($E8,$L$4,$H8) -> 0 | M8: =SUMIF($E8,$M$4,$H8) -> 0 | N8: =SUMIF($E8,$N$4,$H8) -> 0
I9: =SUMIF($E9,$I$4,$H9) -> 0 | J9: =SUMIF($E9,$J$4,$H9) -> 0 | K9: =SUMIF($E9,$K$4,$H9) -> 0 | L9: =SUMIF($E9,$L$4,$H9) -> 0 | M9: =SUMIF($E9,$M$4,$H9) -> 0 | N9: =SUMIF($E9,$N$4,$H9) -> 0
I10: =SUMIF($E10,$I$4,$H10) -> 0 | J10: =SUMIF($E10,$J$4,$H10) -> 0 | K10: =SUMIF($E10,$K$4,$H10) -> 0 | L10: =SUMIF($E10,$L$4,$H10) -> 0 | M10: =SUMIF($E10,$M$4,$H10) -> 0 | N10: =SUMIF($E10,$N$4,$H10) -> 0
I11: =SUMIF($E11,$I$4,$H11) -> 0 | J11: =SUMIF($E11,$J$4,$H11) -> 0 | K11: =SUMIF($E11,$K$4,$H11) -> 0 | L11: =SUMIF($E11,$L$4,$H11) -> 0 | M11: =SUMIF($E11,$M$4,$H11) -> 0 | N11: =SUMIF($E11,$N$4,$H11) -> 0
I12: =SUMIF($E12,$I$4,$H12) -> 0 | J12: =SUMIF($E12,$J$4,$H12) -> 0 | K12: =SUMIF($E12,$K$4,$H12) -> 0 | L12: =SUMIF($E12,$L$4,$H12) -> 0 | M12: =SUMIF($E12,$M$4,$H12) -> 0 | N12: =SUMIF($E12,$N$4,$H12) -> 0
I13: =SUMIF($E13,$I$4,$H13) -> 0 | J13: =SUMIF($E13,$J$4,$H13) -> 0 | K13: =SUMIF($E13,$K$4,$H13) -> 0 | L13: =SUMIF($E13,$L$4,$H13) -> 0 | M13: =SUMIF($E13,$M$4,$H13) -> 0 | N13: =SUMIF($E13,$N$4,$H13) -> 0
I14: =SUMIF($E14,$I$4,$H14) -> 0 | J14: =SUMIF($E14,$J$4,$H14) -> 0 | K14: =SUMIF($E14,$K$4,$H14) -> 0 | L14: =SUMIF($E14,$L$4,$H14) -> 0 | M14: =SUMIF($E14,$M$4,$H14) -> 0 | N14: =SUMIF($E14,$N$4,$H14) -> 0
I15: =SUMIF($E15,$I$4,$H15) -> 0 | J15: =SUMIF($E15,$J$4,$H15) -> 0 | K15: =SUMIF($E15,$K$4,$H15) -> 0 | L15: =SUMIF($E15,$L$4,$H15) -> 0 | M15: =SUMIF($E15,$M$4,$H15) -> 0 | N15: =SUMIF($E15,$N$4,$H15) -> 0
I16: =SUMIF($E16,$I$4,$H16) -> 0 | J16: =SUMIF($E16,$J$4,$H16) -> 0 | K16: =SUMIF($E16,$K$4,$H16) -> 0 | L16: =SUMIF($E16,$L$4,$H16) -> 0 | M16: =SUMIF($E16,$M$4,$H16) -> 0 | N16: =SUMIF($E16,$N$4,$H16) -> 0
... I54: =SUMIF($E54,$I$4,$H54) -> 0 | J54: =SUMIF($E54,$J$4,$H54) -> 0 | K54: =SUMIF($E54,$K$4,$H54) -> 0 | L54: =SUMIF($E54,$L$4,$H54) -> 0 | M54: =SUMIF($E54,$M$4,$H54) -> 0 | N54: =SUMIF($E54,$N$4,$H54) -> 0

Sheet Currency Codes
A1: Code | B1: Currency
A2: ATS | B2: Austrian Schilling
A3: BEF | B3: Belgian Franc
A4: BGL | B4: Bulgarian Lev
A5: CSK | B5: Czech Koruna
A6: CYP | B6: Cypriot Pound
A7: DEM | B7: Deutschmark
A8: DKK | B8: Danish Krone
A9: EEK | B9: Estonian Kroon
A10: ESP | B10: Spanish Peseta
A11: EUR | B11: Euro
A12: FIM | B12: Finnish Markka
... A32: TRL | B32: Turkish Lira

Sheet Subsistence Rates
A1: Country Visited | B1: Rate per Day (EUR)
A2: AT | B2: 122
A3: BE | B3: 150
A4: BG | B4: 157
A5: CY | B5: 100
A6: CZ | B6: 214
A7: DE | B7: 127
A8: DK | B8: 179
A9: EE | B9: 129
A10: EL | B10: 113
A11: ES | B11: 141
A12: FI | B12: 156
A13: FL | B13: 174
... A30: SK | B30: 164
A31: TR | B31: --
A32: UK | B32: 199
