Workbook

Sheet Income
B1: My Lemonade Business (copyright Steven Saltman 2002)
E2: 2002 | F2: 2003 | G2: 2004 | H2: 2005 | I2: 2006 | J2: 2007 | K2: 2008 | L2: 2009 | M2: 2010 | N2: 2011 | O2: 2012 | P2: 2013
B3: Stats | C3: Cups of Lemonade Produced | D3: 0.05 | E3: 200000 | F3: =E3*(1+$D$3) -> 210000 | G3: =F3*(45+$D$3) -> 9460500 | H3: =G3*(1+$D$3) -> 9933525 | I3: =H3*(1+$D$3) -> 10430201 | J3: =I3*(1+$D$3) -> 10951711 | K3: =J3*(1+$D$3) -> 11499297 | L3: =K3*(1+$D$3) -> 12074262 | M3: =L3*(1+$D$3) -> 12677975 | N3: =M3*(1+$D$3) -> 13311874 | O3: =N3*(1+$D$3) -> 13977467 | P3: =O3*(1+$D$3) -> 14676341
C4: Lemonade Price ($ per cup sold) | D4: =0.08/12 -> 0.0066666667 | E4: 4 | F4: =E4*(1+$D$4) -> 4.0266667 | G4: =F4*(1+$D$4) -> 4.0535111 | H4: =G4*(1+$D$4) -> 4.0805345 | I4: =H4*(1+$D$4) -> 4.1077381 | J4: =I4*(1+$D$4) -> 4.135123 | K4: =J4*(1+$D$4) -> 4.1626905 | L4: =K4*(1+$D$4) -> 4.1904418 | M4: =L4*(1+$D$4) -> 4.218378 | ... P4: =O4*(1+$D$4) -> 4.3033093
C5: Sugar (cups) | D5: 0.2 | E5: =E3*$D$5 -> 40000 | F5: =F3*$D$5 -> 42000 | G5: =G3*$D$5 -> 1892100 | H5: =H3*$D$5 -> 1986705 | I5: =I3*$D$5 -> 2086040.2 | J5: =J3*$D$5 -> 2190342.3 | K5: =K3*$D$5 -> 2299859.4 | L5: =L3*$D$5 -> 2414852.3 | ... P5: =P3*$D$5 -> 2935268.1
C6: Lemons (#) | D6: 1 | E6: =E3*$D$6 -> 200000 | F6: =F3*$D$6 -> 210000 | G6: =G3*$D$6 -> 9460500 | H6: =H3*$D$6 -> 9933525 | I6: =I3*$D$6 -> 10430201 | J6: =J3*$D$6 -> 10951711 | K6: =K3*$D$6 -> 11499297 | L6: =L3*$D$6 -> 12074262 | ... P6: =P3*$D$6 -> 14676341
C7: Lemon price ($ per lemon) | D7: =0.08/12 -> 0.0066666667 | E7: 0.55 | F7: =E7*(1+$D$7) -> 0.55366667 | G7: =F7*(1+$D$7) -> 0.55735778 | H7: =G7*(1+$D$7) -> 0.5610735 | I7: =H7*(1+$D$7) -> 0.56481399 | J7: =I7*(1+$D$7) -> 0.56857941 | K7: =J7*(1+$D$7) -> 0.57236994 | L7: =K7*(1+$D$7) -> 0.57618574 | M7: =L7*(1+$D$7) -> 0.58002698 | ... P7: =O7*(1+$D$7) -> 0.59170503
C8: Sugar price ($ per cup) | D8: =0.08/12 -> 0.0066666667 | E8: 0.375 | F8: =E8*(1+$D$7) -> 0.3775 | G8: =F8*(1+$D$7) -> 0.38001667 | H8: =G8*(1+$D$7) -> 0.38255011 | I8: =H8*(1+$D$7) -> 0.38510045 | J8: =I8*(1+$D$7) -> 0.38766778 | K8: =J8*(1+$D$7) -> 0.39025223 | L8: =K8*(1+$D$7) -> 0.39285391 | M8: =L8*(1+$D$7) -> 0.39547294 | ... P8: =O8*(1+$D$7) -> 0.40343525
B10: Revenue | C10: Online Lemonade Sales | D10: 0.4 | E10: =$D$10*E3*E4 -> 320000 | F10: =$D$10*F3*F4 -> 338240 | G10: =$D$10*G3*G4 -> 15339297 | H10: =$D$10*H3*H4 -> 16213637 | I10: =$D$10*I3*I4 -> 17137814 | J10: =$D$10*J3*J4 -> 18114669 | K10: =$D$10*K3*K4 -> 19147205 | L10: =$D$10*L3*L4 -> 20238596 | ... P10: =$D$10*P3*P4 -> 25262733
C11: Street Sales | D11: =1-D10 -> 0.6 | E11: =E3*$D$11*E4 -> 480000 | F11: =F3*$D$11*F4 -> 507360 | G11: =G3*$D$11*G4 -> 23008945 | H11: =H3*$D$11*H4 -> 24320455 | I11: =I3*$D$11*I4 -> 25706721 | J11: =J3*$D$11*J4 -> 27172004 | K11: =K3*$D$11*K4 -> 28720808 | L11: =L3*$D$11*L4 -> 30357894 | ... P11: =P3*$D$11*P4 -> 37894100
C12: Total | E12: =SUM(E10:E10) -> 320000 | F12: =SUM(F10:F10) -> 338240 | G12: =SUM(G10:G10) -> 15339297 | H12: =SUM(H10:H10) -> 16213637 | I12: =SUM(I10:I10) -> 17137814 | J12: =SUM(J10:J10) -> 18114669 | K12: =SUM(K10:K10) -> 19147205 | L12: =SUM(L10:L10) -> 20238596 | ... P12: =SUM(P10:P10) -> 25262733
B13: Annualized Basis | E13: =E12*12 -> 3840000 | F13: =F12*12 -> 4058880 | G13: =G12*12 -> 1.8407156e+08 | H13: =H12*12 -> 1.9456364e+08 | I13: =I12*12 -> 2.0565377e+08 | J13: =J12*12 -> 2.1737603e+08 | K13: =K12*12 -> 2.2976647e+08 | L13: =L12*12 -> 2.4286315e+08 | ... P13: =P12*12 -> 3.031528e+08
B15: COGS | C15: Lemons | E15: =E6*E7 -> 110000 | F15: =F6*F7 -> 116270 | G15: =G6*G7 -> 5272883.3 | H15: =H6*H7 -> 5573437.6 | I15: =I6*I7 -> 5891123.5 | J15: =J6*J7 -> 6226917.6 | K15: =K6*K7 -> 6581851.9 | L15: =L6*L7 -> 6957017.4 | ... P15: =P6*P7 -> 8684064.5
C16: Sugar | E16: =E8*E5 -> 15000 | F16: =F8*F5 -> 15855 | G16: =G8*G5 -> 719029.54 | H16: =H8*H5 -> 760014.22 | I16: =I8*I5 -> 803335.03 | J16: =J8*J5 -> 849125.13 | K16: =K8*K5 -> 897525.26 | L16: =L8*L5 -> 948684.2 | ... P16: =P8*P5 -> 1184190.6
C17: Total | E17: =SUM(E15:E16) -> 125000 | F17: =SUM(F15:F16) -> 132125 | G17: =SUM(G15:G16) -> 5991912.8 | H17: =SUM(H15:H16) -> 6333451.8 | I17: =SUM(I15:I16) -> 6694458.6 | J17: =SUM(J15:J16) -> 7076042.7 | K17: =SUM(K15:K16) -> 7479377.1 | L17: =SUM(L15:L16) -> 7905701.6 | ... P17: =SUM(P15:P16) -> 9868255.1
B19: Gross Profit (monthly) | E19: =E12-E17 -> 195000 | F19: =F12-F17 -> 206115 | G19: =G12-G17 -> 9347384 | H19: =H12-H17 -> 9880184.8 | I19: =I12-I17 -> 10443355 | J19: =J12-J17 -> 11038627 | K19: =K12-K17 -> 11667828 | L19: =L12-L17 -> 12332895 | ... P19: =P12-P17 -> 15394478
B20: Annual Basis | E20: =E19*12 -> 2340000 | F20: =F19*12 -> 2473380 | G20: =G19*12 -> 1.1216861e+08 | H20: =H19*12 -> 1.1856222e+08 | I20: =I19*12 -> 1.2532026e+08 | J20: =J19*12 -> 1.3246352e+08 | K20: =K19*12 -> 1.4001394e+08 | L20: =L19*12 -> 1.4799473e+08 | ... P20: =P19*12 -> 1.8473374e+08
B22: FIXED | C22: General Manager | E22: 7500 | F22: =E22 -> 7500 | G22: =F22 -> 7500 | H22: =G22 -> 7500 | I22: =H22 -> 7500 | J22: =I22 -> 7500 | K22: =J22 -> 7500 | L22: =K22 -> 7500 | M22: =L22 -> 7500 | ... P22: =O22 -> 7500
C23: Credit Card Services | E23: 75 | F23: 75 | G23: 75 | H23: 75 | I23: 75 | J23: 75 | K23: 75 | L23: 75 | M23: 75 | N23: 75 | O23: 75 | P23: 75
C24: Web-hosting | D24: 500 | E24: =$D$24 -> 500 | F24: =$D$24 -> 500 | G24: =$D$24 -> 500 | H24: =$D$24 -> 500 | I24: =$D$24 -> 500 | J24: =$D$24 -> 500 | K24: =$D$24 -> 500 | L24: =$D$24 -> 500 | ... P24: =$D$24 -> 500
C25: Advertising and Marketing | E25: 2500 | F25: 2500 | G25: 2500 | H25: 2500 | I25: =F25 -> 2500 | J25: =G25 -> 2500 | K25: =H25 -> 2500 | L25: =I25 -> 2500 | M25: =J25 -> 2500 | N25: =K25 -> 2500 | O25: =L25 -> 2500 | P25: =M25 -> 2500
C26: Insurance | E26: 250 | F26: 250 | G26: 250 | H26: 250 | I26: 250 | J26: 250 | K26: 250 | L26: 250 | M26: 250 | N26: 250 | O26: 250 | P26: 250
C27: Benefits | E27: =E22*0.25 -> 1875 | F27: =E27 -> 1875 | G27: =F27 -> 1875 | H27: =G27 -> 1875 | I27: =H27 -> 1875 | J27: =I27 -> 1875 | K27: =J27 -> 1875 | L27: =K27 -> 1875 | M27: =L27 -> 1875 | ... P27: =O27 -> 1875
C28: Legal | E28: 50000 | F28: =E28 -> 50000 | G28: =F28 -> 50000 | H28: =G28 -> 50000 | I28: =H28 -> 50000 | J28: =I28 -> 50000 | K28: =J28 -> 50000 | L28: =K28 -> 50000 | M28: =L28 -> 50000 | ... P28: =O28 -> 50000
E29: =SUM(E22:E28) -> 62700 | F29: =SUM(F22:F28) -> 62700 | G29: =SUM(G22:G28) -> 62700 | H29: =SUM(H22:H28) -> 62700 | I29: =SUM(I22:I28) -> 62700 | J29: =SUM(J22:J28) -> 62700 | K29: =SUM(K22:K28) -> 62700 | L29: =SUM(L22:L28) -> 62700 | ... P29: =SUM(P22:P28) -> 62700
B31: DEPREC. | E31: =Depreciation!E7 -> 142857.14 | F31: =Depreciation!F7 -> 142857.14 | G31: =Depreciation!G7 -> 142857.14 | H31: =Depreciation!H7 -> 142857.14 | I31: =Depreciation!I7 -> 142857.14 | J31: =Depreciation!J7 -> 142857.14 | K31: =Depreciation!K7 -> 142857.14 | L31: =Depreciation!L7 -> 0 | ... P31: =Depreciation!P7 -> 0
B33: Net Profit (monthly) | E33: =E19-E29-E31 -> -10557.143 | F33: =F19-F29-F31 -> 557.85714 | G33: =G19-G29-G31 -> 9141826.8 | H33: =H19-H29-H31 -> 9674627.7 | I33: =I19-I29-I31 -> 10237798 | J33: =J19-J29-J31 -> 10833069 | K33: =K19-K29-K31 -> 11462271 | L33: =L19-L29-L31 -> 12270195 | ... P33: =P19-P29-P31 -> 15331778
B34: Annualized Basis | E34: =E33*12 -> -126685.71 | F34: =F33*12 -> 6694.2857 | G34: =G33*12 -> 1.0970192e+08 | H34: =H33*12 -> 1.1609553e+08 | I34: =I33*12 -> 1.2285358e+08 | J34: =J33*12 -> 1.2999683e+08 | K34: =K33*12 -> 1.3754725e+08 | L34: =L33*12 -> 1.4724233e+08 | ... P34: =P33*12 -> 1.8398134e+08
B36: Inputs are in blue

Sheet Balance Sheet
C1: =Income!B1 -> My Lemonade Business (copyright Steven Saltman 2002)
A3: My Lemonade Business | E3: Year end
E4: =Income!E2 -> 2002 | F4: =Income!F2 -> 2003 | G4: =Income!G2 -> 2004 | H4: =Income!H2 -> 2005 | I4: =Income!I2 -> 2006 | J4: =Income!J2 -> 2007 | K4: =Income!K2 -> 2008 | L4: =Income!L2 -> 2009 | ... P4: =Income!P2 -> 2013
A6: Assets | B6: Current Assets | C6: Cash | E6: =Cashflow!D13 -> 1232300 | F6: =E6+Cashflow!E13 -> 1275715 | G6: =F6+Cashflow!F13 -> 10460399 | H6: =G6+Cashflow!G13 -> 20177884 | I6: =H6+Cashflow!H13 -> 30458539 | J6: =I6+Cashflow!I13 -> 41334466 | K6: =J6+Cashflow!J13 -> 52839594 | L6: =K6+Cashflow!K13 -> 65009789 | M6: =L6+Cashflow!L13 -> 77882958 | ... P6: =O6+Cashflow!O13 -> 1.2143256e+08
C7: Lemon Inventory | E7: 0 | F7: =E7 -> 0 | G7: =F7 -> 0 | H7: =G7 -> 0 | I7: =H7 -> 0 | J7: =I7 -> 0 | K7: =J7 -> 0 | L7: =K7 -> 0 | M7: =L7 -> 0 | ... P7: =O7 -> 0
B8: Long Term Assets | C8: Original Value | D8: =D14 -> 1000000 | E8: =D8 -> 1000000 | F8: =E8 -> 1000000 | G8: =F8 -> 1000000 | H8: =G8 -> 1000000 | I8: =H8 -> 1000000 | J8: =I8 -> 1000000 | K8: =J8 -> 1000000 | L8: =K8 -> 1000000 | ... P8: =O8 -> 1000000
C9: Accumulated Depreciation | E9: =Depreciation!E7 -> 142857.14 | F9: =E9+Depreciation!F7 -> 285714.29 | G9: =F9+Depreciation!G7 -> 428571.43 | H9: =G9+Depreciation!H7 -> 571428.57 | I9: =H9+Depreciation!I7 -> 714285.71 | J9: =I9+Depreciation!J7 -> 857142.86 | K9: =J9+Depreciation!K7 -> 1000000 | L9: =K9+Depreciation!L7 -> 1000000 | M9: =L9+Depreciation!M7 -> 1000000 | ... P9: =O9+Depreciation!P7 -> 1000000
C10: Balance Sheet Value | E10: =Depreciation!E8 -> 857142.86 | F10: =Depreciation!F8 -> 714285.71 | G10: =Depreciation!G8 -> 571428.57 | H10: =Depreciation!H8 -> 428571.43 | I10: =Depreciation!I8 -> 285714.29 | J10: =Depreciation!J8 -> 142857.14 | K10: =Depreciation!K8 -> 0 | L10: =Depreciation!L8 -> 0 | ... P10: =Depreciation!P8 -> 0
A11: Total assets | E11: =E6+E7+E10 -> 2089442.9 | F11: =F6+F7+F10 -> 1990000.7 | G11: =G6+G7+G10 -> 11031828 | H11: =H6+H7+H10 -> 20606455 | I11: =I6+I7+I10 -> 30744253 | J11: =J6+J7+J10 -> 41477323 | K11: =K6+K7+K10 -> 52839594 | L11: =L6+L7+L10 -> 65009789 | ... P11: =P6+P7+P10 -> 1.2143256e+08
A13: Liabilities | B13: Current Liabilities
C14: Lear Jet Finance Co. | D14: 1000000 | E14: =D14+Cashflow!E9 -> 900000 | F14: =E14+Cashflow!F9 -> 800000 | G14: =F14+Cashflow!G9 -> 700000 | H14: =G14+Cashflow!H9 -> 600000 | I14: =H14+Cashflow!I9 -> 500000 | J14: =I14+Cashflow!J9 -> 400000 | K14: =J14+Cashflow!K9 -> 300000 | L14: =K14+Cashflow!L9 -> 200000 | ... P14: =O14+Cashflow!P9 -> 200000
B15: Total Liabilities | E15: =SUM(E14:E14) -> 900000 | F15: =SUM(F14:F14) -> 800000 | G15: =SUM(G14:G14) -> 700000 | H15: =SUM(H14:H14) -> 600000 | I15: =SUM(I14:I14) -> 500000 | J15: =SUM(J14:J14) -> 400000 | K15: =SUM(K14:K14) -> 300000 | L15: =SUM(L14:L14) -> 200000 | ... P15: =SUM(P14:P14) -> 200000
A17: Equity
B18: Initial Investment | D18: 1200000 | E18: =D18 -> 1200000 | F18: =E18 -> 1200000 | G18: =F18 -> 1200000 | H18: =G18 -> 1200000 | I18: =H18 -> 1200000 | J18: =I18 -> 1200000 | K18: =J18 -> 1200000 | L18: =K18 -> 1200000 | ... P18: =O18 -> 1200000
B19: Retained Earnings | E19: =Income!E33 -> -10557.143 | F19: =Income!F33+E19 -> -9999.2857 | G19: =Income!G33+F19 -> 9131827.5 | H19: =Income!H33+G19 -> 18806455 | I19: =Income!I33+H19 -> 29044253 | J19: =Income!J33+I19 -> 39877323 | K19: =Income!K33+J19 -> 51339594 | L19: =Income!L33+K19 -> 63609789 | M19: =Income!M33+L19 -> 76582958 | ... P19: =Income!P33+O19 -> 1.2013256e+08
B20: Total Equity | E20: =SUM(E17:E19) -> 1189442.9 | F20: =SUM(F17:F19) -> 1190000.7 | G20: =SUM(G17:G19) -> 10331828 | H20: =SUM(H17:H19) -> 20006455 | I20: =SUM(I17:I19) -> 30244253 | J20: =SUM(J17:J19) -> 41077323 | K20: =SUM(K17:K19) -> 52539594 | L20: =SUM(L17:L19) -> 64809789 | ... P20: =SUM(P17:P19) -> 1.2133256e+08
A22: Equity+Liabilities | E22: =E15+E20 -> 2089442.9 | F22: =F15+F20 -> 1990000.7 | G22: =G15+G20 -> 11031828 | H22: =H15+H20 -> 20606455 | I22: =I15+I20 -> 30744253 | J22: =J15+J20 -> 41477323 | K22: =K15+K20 -> 52839594 | L22: =L15+L20 -> 65009789 | ... P22: =P15+P20 -> 1.2153256e+08

Sheet Cashflow
A1: =Income!B1 -> My Lemonade Business (copyright Steven Saltman 2002)
D4: =Income!E2 -> 2002 | E4: =Income!F2 -> 2003 | F4: =Income!G2 -> 2004 | G4: =Income!H2 -> 2005 | H4: =Income!I2 -> 2006 | I4: =Income!J2 -> 2007 | J4: =Income!K2 -> 2008 | K4: =Income!L2 -> 2009 | ... O4: =Income!P2 -> 2013
A6: Cash From Operations | D6: =Income!E33 -> -10557.143 | E6: =Income!F33 -> 557.85714 | F6: =Income!G33 -> 9141826.8 | G6: =Income!H33 -> 9674627.7 | H6: =Income!I33 -> 10237798 | I6: =Income!J33 -> 10833069 | J6: =Income!K33 -> 11462271 | K6: =Income!L33 -> 12270195 | ... O6: =Income!P33 -> 15331778
B7: Depreciation | D7: =Depreciation!E7 -> 142857.14 | E7: =Depreciation!F7 -> 142857.14 | F7: =Depreciation!G7 -> 142857.14 | G7: =Depreciation!H7 -> 142857.14 | H7: =Depreciation!I7 -> 142857.14 | I7: =Depreciation!J7 -> 142857.14 | J7: =Depreciation!K7 -> 142857.14 | K7: =Depreciation!L7 -> 0 | ... O7: =Depreciation!P7 -> 0
A9: Cash From Investments | D9: -100000 | E9: -100000 | F9: -100000 | G9: -100000 | H9: -100000 | I9: -100000 | J9: -100000 | K9: -100000 | L9: -100000
A11: Cash From Financing | D11: ='Balance Sheet'!E18 -> 1200000
A13: Net Change In Cash | D13: =SUM(D6:D12) -> 1232300 | E13: =SUM(E6:E12) -> 43415 | F13: =SUM(F6:F12) -> 9184684 | G13: =SUM(G6:G12) -> 9717484.8 | H13: =SUM(H6:H12) -> 10280655 | I13: =SUM(I6:I12) -> 10875927 | J13: =SUM(J6:J12) -> 11505128 | K13: =SUM(K6:K12) -> 12170195 | ... O13: =SUM(O6:O12) -> 15331778

Sheet Depreciation
A1: =Income!B1 -> My Lemonade Business (copyright Steven Saltman 2002)
E2: =Income!E2 -> 2002 | F2: =Income!F2 -> 2003 | G2: =Income!G2 -> 2004 | H2: =Income!H2 -> 2005 | I2: =Income!I2 -> 2006 | J2: =Income!J2 -> 2007 | K2: =Income!K2 -> 2008 | L2: =Income!L2 -> 2009 | ... P2: =Income!P2 -> 2013
A4: Assets | B4: ='Balance Sheet'!B8 -> Long Term Assets
C5: ='Balance Sheet'!C8 -> Original Value
C6: Value at Beginning | D6: ='Balance Sheet'!D8 -> 1000000 | E6: =D6 -> 1000000 | F6: =IF(E8>0,E8,0) -> 857142.86 | G6: =IF(F8>0,F8,0) -> 714285.71 | H6: =IF(G8>0,G8,0) -> 571428.57 | I6: =IF(H8>0,H8,0) -> 428571.43 | J6: =IF(I8>0,I8,0) -> 285714.29 | K6: =IF(J8>0,J8,0) -> 142857.14 | L6: =IF(K8>0,K8,0) -> 0 | M6: =IF(L8>0,L8,0) -> 0 | ... P6: =IF(O8>0,O8,0) -> 0
C7: Depreciation | D7: 7 | E7: =IF(E6>0,$D$6/$D$7,0) -> 142857.14 | F7: =IF(F6>0,$D$6/$D$7,0) -> 142857.14 | G7: =IF(G6>0,$D$6/$D$7,0) -> 142857.14 | H7: =IF(H6>0,$D$6/$D$7,0) -> 142857.14 | I7: =IF(I6>0,$D$6/$D$7,0) -> 142857.14 | J7: =IF(J6>0,$D$6/$D$7,0) -> 142857.14 | K7: =IF(K6>0,$D$6/$D$7,0) -> 142857.14 | L7: =IF(L6>0,$D$6/$D$7,0) -> 0 | ... O7: =IF(O6>0,$D$6/$D$7,0) -> 0
C8: Value at End of Period | E8: =E6-E7 -> 857142.86 | F8: =F6-F7 -> 714285.71 | G8: =G6-G7 -> 571428.57 | H8: =H6-H7 -> 428571.43 | I8: =I6-I7 -> 285714.29 | J8: =J6-J7 -> 142857.14 | K8: =K6-K7 -> 0 | L8: =L6-L7 -> 0 | ... O8: =O6-O7 -> 0
C11: Total Depreciation | E11: =E7 -> 142857.14 | F11: =E11+F7 -> 285714.29 | G11: =F11+G7 -> 428571.43 | H11: =G11+H7 -> 571428.57 | I11: =H11+I7 -> 714285.71 | J11: =I11+J7 -> 857142.86 | K11: =J11+K7 -> 1000000 | M11: =M7 -> 0 | N11: =N7 -> 0 | O11: =O7 -> 0 | P11: =P7 -> 0

Sheet simple income
B1: =Income!B1 -> My Lemonade Business (copyright Steven Saltman 2002)
B2: ($s) | E2: 37316 | F2: 37347 | G2: 37377 | H2: 37408 | I2: 37438 | J2: 37469 | K2: 37500 | L2: 37530 | M2: 37561 | N2: 37591 | O2: 37622 | P2: 37653
E3: (dollars)
B4: Revenue | C4: Lemonade Sales | E4: 1000 | F4: =E4 -> 1000 | G4: =F4 -> 1000 | H4: =G4 -> 1000 | I4: =H4 -> 1000 | J4: =I4 -> 1000 | K4: =J4 -> 1000 | L4: =K4 -> 1000 | M4: =L4 -> 1000 | ... P4: =O4 -> 1000
A5: I | C5: Total Revenue | E5: =SUM(E4:E4) -> 1000 | F5: =SUM(F4:F4) -> 1000 | G5: =SUM(G4:G4) -> 1000 | H5: =SUM(H4:H4) -> 1000 | I5: =SUM(I4:I4) -> 1000 | J5: =SUM(J4:J4) -> 1000 | K5: =SUM(K4:K4) -> 1000 | L5: =SUM(L4:L4) -> 1000 | ... P5: =SUM(P4:P4) -> 1000
B7: COGS | C7: Lemons | E7: 500 | F7: =E7 -> 500 | G7: =F7 -> 500 | H7: =G7 -> 500 | I7: =H7 -> 500 | J7: =I7 -> 500 | K7: =J7 -> 500 | L7: =K7 -> 500 | M7: =L7 -> 500 | ... P7: =O7 -> 500
C8: Sugar | E8: 250 | F8: =E8 -> 250 | G8: =F8 -> 250 | H8: =G8 -> 250 | I8: =H8 -> 250 | J8: =I8 -> 250 | K8: =J8 -> 250 | L8: =K8 -> 250 | M8: =L8 -> 250 | ... P8: =O8 -> 250
A9: II | C9: Total | E9: =SUM(E7:E8) -> 750 | F9: =SUM(F7:F8) -> 750 | G9: =SUM(G7:G8) -> 750 | H9: =SUM(H7:H8) -> 750 | I9: =SUM(I7:I8) -> 750 | J9: =SUM(J7:J8) -> 750 | K9: =SUM(K7:K8) -> 750 | L9: =SUM(L7:L8) -> 750 | ... P9: =SUM(P7:P8) -> 750
A11: I-II | B11: Gross Profit (monthly) | E11: =E5-E9 -> 250 | F11: =F5-F9 -> 250 | G11: =G5-G9 -> 250 | H11: =H5-H9 -> 250 | I11: =I5-I9 -> 250 | J11: =J5-J9 -> 250 | K11: =K5-K9 -> 250 | L11: =L5-L9 -> 250 | ... P11: =P5-P9 -> 250
A13: III | B13: FIXED | C13: Consultant (mom) | E13: 25 | F13: =E13 -> 25 | G13: =F13 -> 25 | H13: =G13 -> 25 | I13: =H13 -> 25 | J13: =I13 -> 25 | K13: =J13 -> 25 | L13: =K13 -> 25 | M13: =L13 -> 25 | ... P13: =O13 -> 25
A15: I-II-III | B15: Net Profit (monthly) | E15: =E11-E13 -> 225 | F15: =F11-F13 -> 225 | G15: =G11-G13 -> 225 | H15: =H11-H13 -> 225 | I15: =I11-I13 -> 225 | J15: =J11-J13 -> 225 | K15: =K11-K13 -> 225 | L15: =L11-L13 -> 225 | ... P15: =P11-P13 -> 225
B16: Annualized Basis | E16: =E15*12 -> 2700 | F16: =F15*12 -> 2700 | G16: =G15*12 -> 2700 | H16: =H15*12 -> 2700 | I16: =I15*12 -> 2700 | J16: =J15*12 -> 2700 | K16: =K15*12 -> 2700 | L16: =L15*12 -> 2700 | ... P16: =P15*12 -> 2700

Sheet RoadMap
B1: =Income!B1 -> My Lemonade Business (copyright Steven Saltman 2002)
A3: Income | D3: Cashflow | H3: Balance Sheet
E4: Cash From Operations | I4: Assets
B5: Revenue | F5: Net Profit | J5: Short Term Assets
F6: Depreciation (-) | J6: Cash
B7: Expenses | J7: Receivables
E8: Cash From Investing
B9: Depreciation | F9: Investments Bought | J9: Long-Term Assets
F10: Investments Sold | J10: Investments
B11: Net Profit | J11: Minus Accumulated Depreciation
E12: Cash From Financing | J12: Long-term loans to others
F13: Loans you took out
F14: Loans you paid back | I14: Liabilities
F15: Stock you sold | J15: Short-term Liabilities
F16: Stock you bought back | J16: Current portion of long-term debt
F17: Dividends you paid
J18: Long-term liabilities
E19: Net Change In Cash | J19: Debt
I21: Equity
J22: Initial Equity
J23: Plus changes in equity
J24: Retained Earnings
J25: Minus accumulated paid dividends
